tests/__init__.py
tests/test_any_of_validator.py
tests/test_any_validator.py
tests/test_array_of_validator.py
tests/test_array_validator.py
tests/test_boolean_validator.py
tests/test_enum_validator.py
tests/test_float_validator.py
tests/test_integer_validator.py
tests/test_null_validator.py
tests/test_number_validator.py
tests/test_object_validator.py
tests/test_one_of_validator.py
tests/test_pointer.py
tests/test_string_validator.py
tests/test_timestamp_validator.py
tests/validator_testcase.py
valeera/__init__.py
valeera/abstract_formatter.py
valeera/abstract_validator.py
valeera/errors.py
valeera/formatter.py
valeera/pointer.py
valeera/validator.py
valeera/validator_visitor.py
valeera-0.6.9.dist-info/LICENSE
valeera-0.6.9.dist-info/METADATA
valeera-0.6.9.dist-info/WHEEL
valeera-0.6.9.dist-info/top_level.txt
valeera-0.6.9.dist-info/RECORD
