Metadata-Version: 2.1
Name: valeera
Version: 0.6.9
Summary: Validator for district42 schema
Home-page: https://github.com/nikitanovosibirsk/valeera
Author: Nikita Tsvetkov
Author-email: nikitanovosibirsk@yandex.com
License: MIT
Platform: UNKNOWN
Requires-Python: >=3.6
Requires-Dist: district42 (<1.0)
